epy_python_kit/__init__.py
epy_python_kit/__main__.py
epy_python_kit/sectionproperties_test.py
epy_python_kit/streamlit_test.py
epy_python_kit/vtk_cylinder.py
epy_python_kit-0.2.1.dist-info/entry_points.txt
epy_python_kit-0.2.1.dist-info/LICENSE
epy_python_kit-0.2.1.dist-info/WHEEL
epy_python_kit-0.2.1.dist-info/METADATA
epy_python_kit-0.2.1.dist-info/RECORD
